containmint.py
containmint-0.6.0.dist-info/entry_points.txt
containmint-0.6.0.dist-info/licenses/LICENSE
containmint-0.6.0.dist-info/WHEEL
containmint-0.6.0.dist-info/METADATA
containmint-0.6.0.dist-info/RECORD
