Metadata-Version: 2.4
Name: containmint
Version: 0.6.0
Summary: Create multi-arch containers using native cloud builds.
Author-email: Matt Clay <matt@mystile.com>
Maintainer-email: Matt Clay <matt@mystile.com>, Matt Davis <mrd@redhat.com>
Requires-Python: >=3.11,<3.14
License-Expression: GPL-3.0-or-later
Classifier: Development Status :: 4 - Beta
Classifier: Environment :: Console
Classifier: Intended Audience :: Developers
Classifier: Natural Language :: English
Classifier: Operating System :: POSIX
Classifier: Topic :: Software Development :: Build Tools
Classifier: Topic :: Utilities
License-File: LICENSE
Requires-Dist: ansible-core == 2.19.2
Requires-Dist: argcomplete ; extra == "argcomplete"
Project-URL: Bug Tracker, https://github.com/ansible/containmint/issues
Project-URL: CI: Azure Pipelines, https://dev.azure.com/ansible/containmint/
Project-URL: Changelog, https://github.com/ansible/containmint/blob/main/CHANGELOG.rst
Project-URL: Documentation, https://github.com/ansible/containmint/blob/main/README.rst
Project-URL: Homepage, https://github.com/ansible/containmint
Project-URL: Source Code, https://github.com/ansible/containmint
Provides-Extra: argcomplete
